palaestrai_environments/__init__.py
palaestrai_environments/connect_four/PalaestrAI_Logo_Brain_final.svg.png
palaestrai_environments/connect_four/__init__.py
palaestrai_environments/connect_four/connect_four.py
palaestrai_environments/connect_four/hARL-Logo.svg.png
palaestrai_environments/connect_four/pyboardgame.py
palaestrai_environments/connect_four/connect_four_old/__init__.py
palaestrai_environments/connect_four/connect_four_old/board.py
palaestrai_environments/connect_four/connect_four_old/cell.py
palaestrai_environments/connect_four/connect_four_old/config.py
palaestrai_environments/connect_four/connect_four_old/connect_four.py
palaestrai_environments/connect_four/connect_four_old/text.py
palaestrai_environments/gym/__init__.py
palaestrai_environments/gym/gym_environment.py
palaestrai_environments/random/__init__.py
palaestrai_environments/random/continuous_environment.py
palaestrai_environments/random/discrete_environment.py
palaestrai_environments/tictactoe/__init__.py
palaestrai_environments/tictactoe/tic_tac_toe_environment.py
palaestrai_environments-3.5.5.dist-info/licenses/LICENSE
palaestrai_environments-3.5.5.dist-info/METADATA
palaestrai_environments-3.5.5.dist-info/WHEEL
palaestrai_environments-3.5.5.dist-info/top_level.txt
palaestrai_environments-3.5.5.dist-info/RECORD
